MANIFEST.in
README.md
setup.py
masonite/contrib/dropbox/__init__.py
masonite/contrib/dropbox/drivers/UploadDropboxDriver.py
masonite/contrib/dropbox/drivers/__init__.py
masonite/contrib/dropbox/providers/DropboxProvider.py
masonite/contrib/dropbox/providers/__init__.py
masonite_dropbox_driver.egg-info/PKG-INFO
masonite_dropbox_driver.egg-info/SOURCES.txt
masonite_dropbox_driver.egg-info/dependency_links.txt
masonite_dropbox_driver.egg-info/requires.txt
masonite_dropbox_driver.egg-info/top_level.txt