Metadata-Version: 1.0
Name: masonite-dropbox-driver
Version: 0.0.5
Summary: Dropbox upload driver for the Masonite framework
Home-page: https://github.com/bjorntheart/masonite-dropbox-driver
Author: Bjorn Theart
Author-email: bjorntheart@gmail.com
License: UNKNOWN
Keywords: python web framework,python3,masonite,dropbox
Platform: UNKNOWN
